{"id": "GrimoireLab", "children": [{"id": "https://github.com/chaoss/grimoirelab-perceval", "children": [{"id": "tests", "children": [{"id": ".", "children": [{"id": "tests/test_git.py", "area": 12.881944444444445, "max_area": 12.881944444444445, "height": 1.270517178584436}]}]}, {"id": "perceval", "children": [{"id": "backends", "children": [{"id": "core", "children": [{"id": ".", "children": [{"id": "perceval/backends/core/git.py", "area": 10.666666666666668, "max_area": 10.666666666666668, "height": 0.9600704139856744}]}]}]}]}]}]}