[{"id": "tests/data/jenkins/jenkins_job_no_builds.json", "name": "jenkins_job_no_builds.json", "height": 1.937313342236251, "area": 1.0201388888888892, "max_area": 1.0201388888888892}, {"id": "tests/data/jenkins/jenkins_jobs.json", "name": "jenkins_jobs.json", "height": 0.13623892193759865, "area": 1.0201388888888892, "max_area": 1.0201388888888892}, {"id": "tests/data/jenkins/jenkins_workflow_job_builds.json", "name": "jenkins_workflow_job_builds.json", "height": 3.0232730362996234, "area": 1.0201388888888892, "max_area": 1.0201388888888892}, {"id": "tests/data/jenkins/jenkins_workflow_jobs.json", "name": "jenkins_workflow_jobs.json", "height": 0.17126987981061065, "area": 1.0201388888888892, "max_area": 1.0201388888888892}, {"id": "tests/data/jenkins/jenkins_job_builds.json", "name": "jenkins_job_builds.json", "height": 8.253757435959692, "area": 1.0201388888888892, "max_area": 1.0201388888888892}, {"id": "tests/test_jenkins.py", "name": "test_jenkins.py", "height": 0.8404819715915988, "area": 6.638888888888888, "max_area": 6.638888888888888}, {"id": "perceval/backends/core/jenkins.py", "name": "jenkins.py", "height": 0.3440087410464975, "area": 4.020833333333334, "max_area": 4.020833333333334}]