{"id": "GrimoireLab", "children": [{"id": "https://github.com/chaoss/grimoirelab-perceval", "children": [{"id": "bin", "children": [{"id": ".", "children": [{"id": "bin/perceval", "area": 1.0201388888888892, "max_area": 1.0201388888888892, "height": 0.2002610173606896}]}]}, {"id": "tests", "children": [{"id": "data", "children": [{"id": "slack", "children": [{"id": ".", "children": [{"id": "tests/data/slack/slack_user_U0001.json", "area": 1.0201388888888892, "max_area": 1.0201388888888892, "height": 0.14711059851887826}, {"id": "tests/data/slack/slack_history_empty.json", "area": 1.0201388888888892, "max_area": 1.0201388888888892, "height": 0.10724778438751974}, {"id": "tests/data/slack/slack_history.json", "area": 1.0201388888888892, "max_area": 1.0201388888888892, "height": 0.144694670389705}, {"id": "tests/data/slack/slack_user_U0003.json", "area": 1.0201388888888892, "max_area": 1.0201388888888892, "height": 0.14107077819594513}, {"id": "tests/data/slack/slack_error.json", "area": 1.0201388888888892, "max_area": 1.0201388888888892, "height": 0.10483185625834647}, {"id": "tests/data/slack/slack_history_20150323.json", "area": 1.0201388888888892, "max_area": 1.0201388888888892, "height": 0.13019910161466552}, {"id": "tests/data/slack/slack_history_next.json", "area": 1.0201388888888892, "max_area": 1.0201388888888892, "height": 0.1229513172271458}, {"id": "tests/data/slack/slack_user_U0002.json", "area": 1.0201388888888892, "max_area": 1.0201388888888892, "height": 0.14348670632511834}]}]}]}, {"id": ".", "children": [{"id": "tests/test_slack.py", "area": 5.4305555555555545, "max_area": 5.4305555555555545, "height": 0.54332281170329}]}]}, {"id": "perceval", "children": [{"id": "backends", "children": [{"id": "core", "children": [{"id": ".", "children": [{"id": "perceval/backends/core/slack.py", "area": 4.222222222222221, "max_area": 4.222222222222221, "height": 0.3452167051110841}]}]}]}]}, {"id": ".", "children": [{"id": "README.md", "area": 1.0201388888888892, "max_area": 1.0201388888888892, "height": 0.3452167051110841}]}]}]}