[
  {
    "name": "kbn_network",
    "size": 10
  },
  {
    "name": "Maria",
    "size": 5
  },
  {
    "name": "Dave",
    "size": 9
  },
  {
    "name": "Jhon",
    "size": 12
  },
  {
    "name": "Sara",
    "size": 12
  },
  {
    "name": "Lemar",
    "size": 12
  },
  {
    "name": "Dawn",
    "size": 12
  },
  {
    "name": "Jesus",
    "size": 8
  },
  {
    "name": "Bitergia",
    "size": 3
  },
  {
    "name": "URJC",
    "size": 6
  },
  {
    "name": "Alice",
    "size": 22
  },
  {
    "name": "Pete",
    "size": 12
  },
  {
    "name": "Seth",
    "size": 6
  },
  {
    "name": "Martin",
    "size": 9
  }
]