[{"id":"GrimoireLab","children":[{"id":"https://github.com/chaoss/grimoirelab-perceval","children":[{"id":"/perceval","children":[{"id":"/perceval/backends","children":[{"id":"/perceval/backends/.","children":[{"id":"perceval/backends/mediawiki.py","area":5.833333333333334,"max_area":6.4375,"height":0.514331674153211},{"id":"perceval/backends/github.py","area":5.229166666666667,"max_area":5.833333333333334,"height":0.4563493990530533},{"id":"perceval/backends/jira.py","area":4.020833333333334,"max_area":5.430555555555555,"height":0.38507951924244255},{"id":"perceval/backends/remo.py","area":3.618055555555556,"max_area":4.222222222222222,"height":0.3403848488527376},{"id":"perceval/backends/gerrit.py","area":4.423611111111111,"max_area":5.027777777777778,"height":0.4672210756343328},{"id":"perceval/backends/__init__.py","area":1,"max_area":1.8055555555555556,"height":0.144694670389705},{"id":"perceval/backends/bugzillarest.py","area":5.833333333333334,"max_area":6.4375,"height":0.4865485006677188},{"id":"perceval/backends/mbox.py","area":5.430555555555555,"max_area":6.034722222222222,"height":0.4080308364695884},{"id":"perceval/backends/git.py","area":7.041666666666667,"max_area":7.645833333333334,"height":0.6532475415806724},{"id":"perceval/backends/discourse.py","area":4.423611111111111,"max_area":5.027777777777778,"height":0.38991137550078914},{"id":"perceval/backends/bugzilla.py","area":6.840277777777778,"max_area":7.444444444444445,"height":0.5324511351220104},{"id":"perceval/backends/stackexchange.py","area":3.8194444444444446,"max_area":4.423611111111111,"height":0.34884059730484396},{"id":"perceval/backends/pipermail.py","area":3.2152777777777777,"max_area":3.618055555555556,"height":0.30293796285055236},{"id":"perceval/backends/gmane.py","area":1.6041666666666667,"max_area":4.625,"height":0.14711059851887823},{"id":"perceval/backends/jenkins.py","area":3.2152777777777777,"max_area":3.8194444444444446,"height":0.26307514871919385},{"id":"perceval/backends/remo2.py","area":3.618055555555556,"max_area":4.222222222222222,"height":-0.2},{"id":"perceval/backends/kitsune.py","area":4.222222222222222,"max_area":4.826388888888889,"height":-0.2},{"id":"perceval/backends/phabricator.py","area":4.222222222222222,"max_area":7.243055555555555,"height":-0.2},{"id":"perceval/backends/telegram.py","area":3.013888888888889,"max_area":4.625,"height":-0.2},{"id":"perceval/backends/confluence.py","area":4.222222222222222,"max_area":4.826388888888889,"height":-0.2},{"id":"perceval/backends/core/confluence.py","area":4.423611111111111,"max_area":12.07638888888889,"height":-0.2},{"id":"perceval/backends/core/github.py","area":5.430555555555555,"max_area":12.07638888888889,"height":-0.2},{"id":"perceval/backends/core/mbox.py","area":5.229166666666667,"max_area":12.07638888888889,"height":-0.2},{"id":"perceval/backends/core/mediawiki.py","area":6.034722222222222,"max_area":12.07638888888889,"height":-0.2},{"id":"perceval/backends/core/redmine.py","area":5.833333333333334,"max_area":12.07638888888889,"height":-0.2},{"id":"perceval/backends/core/supybot.py","area":4.423611111111111,"max_area":12.07638888888889,"height":-0.2},{"id":"perceval/backends/core/bugzilla.py","area":7.041666666666667,"max_area":12.07638888888889,"height":-0.2},{"id":"perceval/backends/core/bugzillarest.py","area":6.034722222222222,"max_area":12.07638888888889,"height":-0.2},{"id":"perceval/backends/core/gmane.py","area":4.423611111111111,"max_area":12.07638888888889,"height":-0.2},{"id":"perceval/backends/core/jira.py","area":5.027777777777778,"max_area":12.07638888888889,"height":-0.2},{"id":"perceval/backends/core/pipermail.py","area":3.416666666666667,"max_area":12.07638888888889,"height":-0.2},{"id":"perceval/backends/core/stackexchange.py","area":4.020833333333334,"max_area":12.07638888888889,"height":-0.2},{"id":"perceval/backends/core/rss.py","area":3.416666666666667,"max_area":12.07638888888889,"height":-0.2},{"id":"perceval/backends/core/gerrit.py","area":4.826388888888889,"max_area":12.07638888888889,"height":-0.2},{"id":"perceval/backends/core/askbot.py","area":5.430555555555555,"max_area":12.07638888888889,"height":-0.2},{"id":"perceval/backends/core/slack.py","area":4.625,"max_area":12.07638888888889,"height":-0.2},{"id":"perceval/backends/core/dockerhub.py","area":3.416666666666667,"max_area":12.07638888888889,"height":-0.2},{"id":"perceval/backends/core/git.py","area":10.0625,"max_area":12.07638888888889,"height":-0.2},{"id":"perceval/backends/core/telegram.py","area":4.222222222222222,"max_area":12.07638888888889,"height":-0.2},{"id":"perceval/backends/core/discourse.py","area":4.625,"max_area":12.07638888888889,"height":-0.2},{"id":"perceval/backends/core/phabricator.py","area":6.840277777777778,"max_area":12.07638888888889,"height":-0.2},{"id":"perceval/backends/core/hyperkitty.py","area":2.8125,"max_area":12.07638888888889,"height":-0.2},{"id":"perceval/backends/core/nntp.py","area":3.618055555555556,"max_area":12.07638888888889,"height":-0.2},{"id":"perceval/backends/core/jenkins.py","area":3.416666666666667,"max_area":12.07638888888889,"height":-0.2},{"id":"perceval/backends/core/meetup.py","area":4.826388888888889,"max_area":12.07638888888889,"height":-0.2},{"id":"perceval/backends/core/gitlab.py","area":6.034722222222222,"max_area":12.07638888888889,"height":-0.2},{"id":"perceval/backends/core/launchpad.py","area":7.444444444444445,"max_area":12.07638888888889,"height":-0.2},{"id":"perceval/backends/core/groupsio.py","area":4.222222222222222,"max_area":12.07638888888889,"height":-0.2},{"id":"perceval/backends/core/mattermost.py","area":5.229166666666667,"max_area":12.07638888888889,"height":-0.2},{"id":"perceval/backends/core/twitter.py","area":4.222222222222222,"max_area":12.07638888888889,"height":-0.2},{"id":"perceval/backends/core/googlehits.py","area":3.618055555555556,"max_area":12.07638888888889,"height":-0.2},{"id":"perceval/backends/redmine.py","area":5.027777777777778,"max_area":6.236111111111112,"height":-0.2},{"id":"perceval/backends/supybot.py","area":4.826388888888889,"max_area":4.826388888888889,"height":-0.2},{"id":"perceval/backends/meetup.py","area":2.0069444444444446,"max_area":5.229166666666667,"height":-0.2},{"id":"perceval/backends/askbot.py","area":6.034722222222222,"max_area":6.034722222222222,"height":-0.2},{"id":"perceval/backends/core/kitsune.py","area":4.826388888888889,"max_area":12.07638888888889,"height":-0.2},{"id":"perceval/backends/core/remo2.py","area":4.222222222222222,"max_area":12.07638888888889,"height":-0.2},{"id":"perceval/backends/core/__init__.py","area":1,"max_area":12.07638888888889,"height":-0.2},{"id":"perceval/backends/core/gitter.py","area":4.423611111111111,"max_area":12.07638888888889,"height":-0.2},{"id":"perceval/backends/core/pagure.py","area":5.027777777777778,"max_area":12.07638888888889,"height":-0.2},{"id":"perceval/backends/core/remo.py","area":4.222222222222222,"max_area":12.07638888888889,"height":-0.2},{"id":"perceval/backends/core/githubql.py","area":3.2152777777777777,"max_area":12.07638888888889,"height":-0.2}]}]},{"id":"/perceval/.","children":[{"id":"perceval/backend.py","area":4.222222222222222,"max_area":11.472222222222223,"height":0.26186718465460723},{"id":"perceval/errors.py","area":1.4027777777777777,"max_area":1.8055555555555556,"height":0.13261502974383876},{"id":"perceval/utils.py","area":2.8125,"max_area":4.625,"height":0.19905305329610296},{"id":"perceval/_version.py","area":1,"max_area":1,"height":0.10120796406458663},{"id":"perceval/cache.py","area":2.2083333333333335,"max_area":2.4097222222222223,"height":0.1616061672939177},{"id":"perceval/__init__.py","area":1,"max_area":1,"height":0.10362389219375986}]}]},{"id":"/tests","children":[{"id":"/tests/data","children":[{"id":"/tests/data/jira","children":[{"id":"/tests/data/jira/.","children":[{"id":"tests/data/jira/jira_issues_page_1.json","area":1.020138888888889,"max_area":1.020138888888889,"height":0.42977418963214753},{"id":"tests/data/jira/jira_issues_page_2.json","area":1.020138888888889,"max_area":1.020138888888889,"height":0.2666990409129537},{"id":"tests/data/jira/jira_issues_page_empty.json","area":1.020138888888889,"max_area":1.020138888888889,"height":0.10724778438751974},{"id":"tests/data/jira/jira_issues_parse_expected.json","area":1.020138888888889,"max_area":1.020138888888889,"height":0.4225264052446278},{"id":"tests/data/jira/jira_comments_issue_page_2.json","area":1.020138888888889,"max_area":1.020138888888889,"height":-0.2},{"id":"tests/data/jira/jira_comments_issue_empty.json","area":1.020138888888889,"max_area":1.020138888888889,"height":-0.2},{"id":"tests/data/jira/jira_comments_issue_page_1.json","area":1.020138888888889,"max_area":1.020138888888889,"height":-0.2},{"id":"tests/data/jira/jira_fields.json","area":1.020138888888889,"max_area":1.020138888888889,"height":-0.2}]}]},{"id":"/tests/data/.","children":[{"id":"tests/data/remo_events_1_2.json","area":1.020138888888889,"max_area":1.020138888888889,"height":0.20509287361903605},{"id":"tests/data/remo_events_empty.json","area":1.020138888888889,"max_area":1.020138888888889,"height":0.11207964064586622},{"id":"tests/data/remo_reps.json","area":1.020138888888889,"max_area":1.020138888888889,"height":1.0289243656671117},{"id":"tests/data/mediawiki_page_476583_revisions.json","area":1.020138888888889,"max_area":1.020138888888889,"height":4.891993444215125},{"id":"tests/data/mediawiki_pages_all_empty.json","area":1.020138888888889,"max_area":1.020138888888889,"height":0.1108716765812796},{"id":"tests/data/mediawiki_pages_allrevisions.json","area":1.020138888888889,"max_area":1.020138888888889,"height":0.14831856258346485},{"id":"tests/data/bugzilla_rest_bugs_empty.json","area":1.020138888888889,"max_area":1.020138888888889,"height":0.10362389219375986},{"id":"tests/data/bugzilla_rest_bug_attachments.json","area":1.020138888888889,"max_area":1.020138888888889,"height":-0.2},{"id":"tests/data/bugzilla_rest_bugs_comments_empty.json","area":1.020138888888889,"max_area":1.020138888888889,"height":0.10845574845210636},{"id":"tests/data/mbox_complex.mbox","area":1.020138888888889,"max_area":1.020138888888889,"height":0.1},{"id":"tests/data/gittest.tar.gz","area":1.020138888888889,"max_area":1.020138888888889,"height":0.1},{"id":"tests/data/github_request_from_2016_03_01","area":1.020138888888889,"max_area":1.020138888888889,"height":0.1},{"id":"tests/data/pipermail_2016_april.mbox","area":1.020138888888889,"max_area":1.020138888888889,"height":0.1},{"id":"tests/data/pipermail_index.html","area":1.020138888888889,"max_area":1.020138888888889,"height":0.15919023916474445},{"id":"tests/data/discourse_posts.json","area":1.020138888888889,"max_area":1.020138888888889,"height":0.10120796406458663},{"id":"tests/data/discourse_posts_chunk.json","area":1.020138888888889,"max_area":1.020138888888889,"height":-0.2},{"id":"tests/data/discourse_topic.json","area":1.020138888888889,"max_area":1.020138888888889,"height":-0.2},{"id":"tests/data/discourse_topic_1149.json","area":1.020138888888889,"max_area":1.020138888888889,"height":1.3611144834284326},{"id":"tests/data/bugzilla_rest_bug_comments.json","area":1.020138888888889,"max_area":1.020138888888889,"height":-0.2},{"id":"tests/data/git_log_incompleted.txt","area":1.020138888888889,"max_area":1.020138888888889,"height":0.1},{"id":"tests/data/jenkins_job_builds.json","area":1.020138888888889,"max_area":1.020138888888889,"height":0.10120796406458663},{"id":"tests/data/github_empty_request","area":1.020138888888889,"max_area":1.020138888888889,"height":0.1},{"id":"tests/data/github_login","area":1.020138888888889,"max_area":1.020138888888889,"height":0.1},{"id":"tests/data/github_request_expected","area":1.020138888888889,"max_area":1.020138888888889,"height":0.1},{"id":"tests/data/github_issue_expected_2","area":1.020138888888889,"max_area":1.020138888888889,"height":0.1},{"id":"tests/data/git_log_empty.txt","area":1.020138888888889,"max_area":1.020138888888889,"height":0.1},{"id":"tests/data/git_bad_cr.txt","area":1.020138888888889,"max_area":1.020138888888889,"height":0.1},{"id":"tests/data/bugzilla_version.xml","area":1.020138888888889,"max_area":1.020138888888889,"height":0.10845574845210636},{"id":"tests/data/git_bad_encoding.txt","area":1.020138888888889,"max_area":1.020138888888889,"height":0.1},{"id":"tests/data/git_log.txt","area":1.020138888888889,"max_area":1.020138888888889,"height":0.1},{"id":"tests/data/pipermail_2015_november.mbox","area":1.020138888888889,"max_area":1.020138888888889,"height":0.1},{"id":"tests/data/github_issue_1","area":1.020138888888889,"max_area":1.020138888888889,"height":0.1},{"id":"tests/data/github_issue_2","area":1.020138888888889,"max_area":1.020138888888889,"height":0.1},{"id":"tests/data/bugzilla_bug_activity_not_valid.html","area":1.020138888888889,"max_area":1.020138888888889,"height":0.38870341143620246},{"id":"tests/data/bugzilla_bugs_details.xml","area":1.020138888888889,"max_area":1.020138888888889,"height":0.3862874833070292},{"id":"tests/data/bugzilla_bugs_invalid_chars.xml","area":1.020138888888889,"max_area":1.020138888888889,"height":0.4261502974383877},{"id":"tests/data/bugzilla_no_version.xml","area":1.020138888888889,"max_area":1.020138888888889,"height":0.10724778438751974},{"id":"tests/data/bugzilla_rest_bugs_history_empty.json","area":1.020138888888889,"max_area":1.020138888888889,"height":0.1108716765812796},{"id":"tests/data/discourse_topic_1150.json","area":1.020138888888889,"max_area":1.020138888888889,"height":1.3611144834284326},{"id":"tests/data/discourse_topics_pinned.json","area":1.020138888888889,"max_area":1.020138888888889,"height":0.2932742503338594},{"id":"tests/data/gmane_messages.mbox","area":1.020138888888889,"max_area":1.020138888888889,"height":0.1},{"id":"tests/data/stackexchange_question_parse","area":1.020138888888889,"max_area":1.020138888888889,"height":0.1},{"id":"tests/data/mediawiki_pages_recent_changes.json","area":1.020138888888889,"max_area":1.020138888888889,"height":0.13382299380842538},{"id":"tests/data/remo_events_2_2.json","area":1.020138888888889,"max_area":1.020138888888889,"height":0.2014689814252762},{"id":"tests/data/bugzilla_rest_bugs_attachments_empty.json","area":1.020138888888889,"max_area":1.020138888888889,"height":0.10724778438751974},{"id":"tests/data/mediawiki_page_592384_revisions.json","area":1.020138888888889,"max_area":1.020138888888889,"height":0.13744688600218527},{"id":"tests/data/stackexchange_question","area":1.020138888888889,"max_area":1.020138888888889,"height":0.1},{"id":"tests/data/discourse_post_raw.json","area":1.020138888888889,"max_area":1.020138888888889,"height":-0.2},{"id":"tests/data/bugzilla_bug_activity_empty_alt.html","area":1.020138888888889,"max_area":1.020138888888889,"height":0.3923273036299624},{"id":"tests/data/mbox_multipart.mbox","area":1.020138888888889,"max_area":1.020138888888889,"height":0.1},{"id":"tests/data/mbox_unknown_encoding.mbox","area":1.020138888888889,"max_area":1.020138888888889,"height":0.1},{"id":"tests/data/jenkins_job_builds_empty.json","area":1.020138888888889,"max_area":1.020138888888889,"height":0.10120796406458663},{"id":"tests/data/jenkins_build.json","area":1.020138888888889,"max_area":1.020138888888889,"height":0.31622556756100517},{"id":"tests/data/bugzilla_bug_activity.html","area":1.020138888888889,"max_area":1.020138888888889,"height":0.38145562704868274},{"id":"tests/data/bugzilla_bugs_details_not_valid.xml","area":1.020138888888889,"max_area":1.020138888888889,"height":0.2207964064586621},{"id":"tests/data/bugzilla_bug_activity_empty.html","area":1.020138888888889,"max_area":1.020138888888889,"height":0.3923273036299624},{"id":"tests/data/github_request","area":1.020138888888889,"max_area":1.020138888888889,"height":0.1},{"id":"tests/data/github_issue_expected_1","area":1.020138888888889,"max_area":1.020138888888889,"height":0.1},{"id":"tests/data/pipermail_2016_march.mbox","area":1.020138888888889,"max_area":1.020138888888889,"height":0.1},{"id":"tests/data/jenkins_jobs.json","area":1.020138888888889,"max_area":1.020138888888889,"height":0.10120796406458663},{"id":"tests/data/mediawiki_namespaces.json","area":1.020138888888889,"max_area":1.020138888888889,"height":0.46480514750515955},{"id":"tests/data/stackexchange_question_page_2","area":1.020138888888889,"max_area":1.020138888888889,"height":0.1},{"id":"tests/data/bugzilla_buglist_next.csv","area":1.020138888888889,"max_area":1.020138888888889,"height":0.1},{"id":"tests/data/bugzilla_bugs_details_next.xml","area":1.020138888888889,"max_area":1.020138888888889,"height":0.21234065800655577},{"id":"tests/data/discourse_topic_1148.json","area":1.020138888888889,"max_area":1.020138888888889,"height":2.438618429039699},{"id":"tests/data/discourse_topics.json","area":1.020138888888889,"max_area":1.020138888888889,"height":0.23529197523370157},{"id":"tests/data/mediawiki_pages_all.json","area":1.020138888888889,"max_area":1.020138888888889,"height":0.1229513172271458},{"id":"tests/data/mediawiki_pages_allrevisions_empty.json","area":1.020138888888889,"max_area":1.020138888888889,"height":0.11691149690421271},{"id":"tests/data/mediawiki_siteinfo_1.23.json","area":1.020138888888889,"max_area":1.020138888888889,"height":0.1845574845210635},{"id":"tests/data/bugzilla_rest_bugs.json","area":1.020138888888889,"max_area":1.020138888888889,"height":0.3005220347213791},{"id":"tests/data/pipermail_apache_index.html","area":1.020138888888889,"max_area":1.020138888888889,"height":0.17006191574602403},{"id":"tests/data/bugzilla_rest_bugs_comments.json","area":1.020138888888889,"max_area":1.020138888888889,"height":0.22442029865242197},{"id":"tests/data/pipermail_index_empty.html","area":1.020138888888889,"max_area":1.020138888888889,"height":0.1229513172271458},{"id":"tests/data/stackexchange_question_page","area":1.020138888888889,"max_area":1.020138888888889,"height":0.1},{"id":"tests/data/discourse_post.json","area":1.020138888888889,"max_area":1.020138888888889,"height":0.1555663469709846},{"id":"tests/data/discourse_topics_empty.json","area":1.020138888888889,"max_area":1.020138888888889,"height":0.11207964064586622},{"id":"tests/data/bugzilla_rest_bug_history.json","area":1.020138888888889,"max_area":1.020138888888889,"height":-0.2},{"id":"tests/data/jenkins_jobs_empty.json","area":1.020138888888889,"max_area":1.020138888888889,"height":0.10120796406458663},{"id":"tests/data/github_orgs","area":1.020138888888889,"max_area":1.020138888888889,"height":0.1},{"id":"tests/data/mbox_no_fields.mbox","area":1.020138888888889,"max_area":1.020138888888889,"height":0.1},{"id":"tests/data/bugzilla_buglist.csv","area":1.020138888888889,"max_area":1.020138888888889,"height":0.1},{"id":"tests/data/xml_invalid.xml","area":1.020138888888889,"max_area":1.020138888888889,"height":0.11570353283962609},{"id":"tests/data/bugzilla_bug.xml","area":1.020138888888889,"max_area":1.020138888888889,"height":0.20509287361903605},{"id":"tests/data/bugzilla_rest_bugs_next.json","area":1.020138888888889,"max_area":1.020138888888889,"height":0.2884423940755129},{"id":"tests/data/bugzilla_rest_bugs_attachments.json","area":1.020138888888889,"max_area":1.020138888888889,"height":0.13019910161466552},{"id":"tests/data/bugzilla_rest_bugs_history.json","area":1.020138888888889,"max_area":1.020138888888889,"height":0.22200437052324873},{"id":"tests/data/mediawiki_siteinfo_1.28.json","area":1.020138888888889,"max_area":1.020138888888889,"height":0.214756586135729},{"id":"tests/data/mbox_single.mbox","area":1.020138888888889,"max_area":1.020138888888889,"height":0.1}]}]},{"id":"/tests/.","children":[{"id":"tests/test_bugzilla.py","area":7.444444444444445,"max_area":8.854166666666668,"height":0.8803447857229573},{"id":"tests/test_git.py","area":7.847222222222222,"max_area":15.5,"height":0.5904334102221682},{"id":"tests/test_jenkins.py","area":4.222222222222222,"max_area":6.638888888888889,"height":0.3343450285298045},{"id":"tests/test_mediawiki.py","area":6.840277777777778,"max_area":8.45138888888889,"height":0.4877564647323054},{"id":"tests/test_remo.py","area":4.423611111111111,"max_area":4.826388888888889,"height":0.31743353162559185},{"id":"tests/test_stackexchange.py","area":4.222222222222222,"max_area":5.833333333333334,"height":0.37783173485492283},{"id":"tests/test_github.py","area":5.229166666666667,"max_area":14.291666666666668,"height":0.6399599368702197},{"id":"tests/test_bugzillarest.py","area":5.229166666666667,"max_area":6.4375,"height":0.5843935898992351},{"id":"tests/test_gmane.py","area":1.8055555555555556,"max_area":6.236111111111112,"height":0.15798227510015783},{"id":"tests/test_utils.py","area":4.423611111111111,"max_area":6.638888888888889,"height":0.34159281291732424},{"id":"tests/test_mbox.py","area":5.229166666666667,"max_area":7.444444444444445,"height":0.4358140099550807},{"id":"tests/test_pipermail.py","area":4.423611111111111,"max_area":6.840277777777778,"height":0.4394379021488406},{"id":"tests/test_discourse.py","area":5.229166666666667,"max_area":8.45138888888889,"height":0.6109687993201407},{"id":"tests/test_backend.py","area":4.020833333333334,"max_area":30,"height":0.2207964064586621},{"id":"tests/test_errors.py","area":2.611111111111111,"max_area":3.2152777777777777,"height":0.1519424547772247},{"id":"tests/test_jira.py","area":4.826388888888889,"max_area":6.4375,"height":0.45755736311763984},{"id":"tests/test_cache.py","area":2.4097222222222223,"max_area":3.618055555555556,"height":0.19301323297316983},{"id":"tests/run_tests.py","area":1,"max_area":1,"height":0.10724778438751974},{"id":"tests/__init__.py","area":1,"max_area":1,"height":0.1}]}]},{"id":"/bin","children":[{"id":"/bin/.","children":[{"id":"bin/perceval","area":1.020138888888889,"max_area":1.020138888888889,"height":0.1918052689085832}]}]},{"id":"/docs","children":[{"id":"/docs/.","children":[{"id":"docs/conf.py","area":1,"max_area":1,"height":0.14711059851887823},{"id":"docs/index.rst","area":1.020138888888889,"max_area":1.020138888888889,"height":0.1},{"id":"docs/howto_doc.rst","area":1.020138888888889,"max_area":1.020138888888889,"height":0.1},{"id":"docs/Makefile","area":1.020138888888889,"max_area":1.020138888888889,"height":0.2884423940755129},{"id":"docs/contributing.rst","area":1.020138888888889,"max_area":1.020138888888889,"height":0.1},{"id":"docs/howto_pkg.rst","area":1.020138888888889,"max_area":1.020138888888889,"height":-0.2}]}]},{"id":"/docker","children":[{"id":"/docker/images","children":[{"id":"/docker/images/perceval","children":[{"id":"/docker/images/perceval/master","children":[{"id":"/docker/images/perceval/master/.","children":[{"id":"docker/images/perceval/master/Dockerfile","area":1.020138888888889,"max_area":1.020138888888889,"height":-0.2}]}]},{"id":"/docker/images/perceval/.","children":[{"id":"docker/images/perceval/README.md","area":1.020138888888889,"max_area":1.020138888888889,"height":-0.2}]}]},{"id":"/docker/images/master","children":[{"id":"/docker/images/master/.","children":[{"id":"docker/images/master/Dockerfile","area":1.020138888888889,"max_area":1.020138888888889,"height":0.11449556877503946}]}]},{"id":"/docker/images/.","children":[{"id":"docker/images/Makefile","area":1.020138888888889,"max_area":1.020138888888889,"height":0.12053538909797257},{"id":"docker/images/README.md","area":1.020138888888889,"max_area":1.020138888888889,"height":0.12657520942090567}]}]}]},{"id":".","children":[{"id":"README.md","area":1.020138888888889,"max_area":1.020138888888889,"height":0.22925215491076847},{"id":"setup.py","area":1,"max_area":1.6041666666666667,"height":0.11328760471045284},{"id":".gitignore","area":1.020138888888889,"max_area":1.020138888888889,"height":0.1},{"id":"NEWS","area":1.020138888888889,"max_area":1.020138888888889,"height":0.1},{"id":".travis.yml","area":1.020138888888889,"max_area":1.020138888888889,"height":0.11811946096879933},{"id":"AUTHORS","area":1.020138888888889,"max_area":1.020138888888889,"height":0.1},{"id":"requirements.txt","area":1.020138888888889,"max_area":1.020138888888889,"height":0.1},{"id":"LICENSE","area":1.020138888888889,"max_area":1.020138888888889,"height":0.1}]}]}]}]